rendercv_fonts/__init__.py
rendercv_fonts/EB Garamond/EBGaramond-Bold.ttf
rendercv_fonts/EB Garamond/EBGaramond-BoldItalic.ttf
rendercv_fonts/EB Garamond/EBGaramond-Italic.ttf
rendercv_fonts/EB Garamond/EBGaramond-Regular.ttf
rendercv_fonts/EB Garamond/OFL.txt
rendercv_fonts/Font Awesome 7/Font Awesome 7 Free-Regular-400.otf
rendercv_fonts/Font Awesome 7/Font Awesome 7 Free-Solid-900.otf
rendercv_fonts/Font Awesome 7/LICENSE.txt
rendercv_fonts/Fontin/Fontin-Bold.otf
rendercv_fonts/Fontin/Fontin-Italic.otf
rendercv_fonts/Fontin/Fontin-Regular.otf
rendercv_fonts/Gentium Book Plus/GentiumBookPlus-Bold.ttf
rendercv_fonts/Gentium Book Plus/GentiumBookPlus-BoldItalic.ttf
rendercv_fonts/Gentium Book Plus/GentiumBookPlus-Italic.ttf
rendercv_fonts/Gentium Book Plus/GentiumBookPlus-Regular.ttf
rendercv_fonts/Gentium Book Plus/OFL.txt
rendercv_fonts/Lato/Lato-Bold.ttf
rendercv_fonts/Lato/Lato-BoldItalic.ttf
rendercv_fonts/Lato/Lato-Italic.ttf
rendercv_fonts/Lato/Lato-Regular.ttf
rendercv_fonts/Lato/OFL.txt
rendercv_fonts/Mukta/Mukta-Bold.ttf
rendercv_fonts/Mukta/Mukta-Regular.ttf
rendercv_fonts/Mukta/OFL.txt
rendercv_fonts/Noto Sans/NotoSans-Bold.ttf
rendercv_fonts/Noto Sans/NotoSans-BoldItalic.ttf
rendercv_fonts/Noto Sans/NotoSans-Italic.ttf
rendercv_fonts/Noto Sans/NotoSans-Regular.ttf
rendercv_fonts/Noto Sans/NotoSansJP-Bold.ttf
rendercv_fonts/Noto Sans/NotoSansJP-Regular.ttf
rendercv_fonts/Noto Sans/NotoSansKR-Bold.ttf
rendercv_fonts/Noto Sans/NotoSansKR-Regular.ttf
rendercv_fonts/Noto Sans/NotoSansSC-Bold.ttf
rendercv_fonts/Noto Sans/NotoSansSC-Regular.ttf
"rendercv_fonts/Noto Sans/OFL JP, KR, SC.txt"
rendercv_fonts/Noto Sans/OFL.txt
rendercv_fonts/Open Sans/OFL.txt
rendercv_fonts/Open Sans/OpenSans-Bold.ttf
rendercv_fonts/Open Sans/OpenSans-BoldItalic.ttf
rendercv_fonts/Open Sans/OpenSans-Italic.ttf
rendercv_fonts/Open Sans/OpenSans-Regular.ttf
rendercv_fonts/Open Sauce Sans/OFL.txt
rendercv_fonts/Open Sauce Sans/OpenSauceSans-Bold.ttf
rendercv_fonts-0.5.0.dist-info/METADATA
rendercv_fonts-0.5.0.dist-info/WHEEL
rendercv_fonts-0.5.0.dist-info/licenses/LICENSE
rendercv_fonts-0.5.0.dist-info/RECORD
